<?xml version="1.0" encoding="UTF-8"?>
<VNCLASS ID="illustrate-25.3" ladl="37M1[-N0 V N2 (E+Loc N1 destination)] ou 37M2[-N0 V N2 (E+Loc N1 destination)] ou 37M3[-N0 V N2 (E+Loc N1 destination)] ou 37M4[-N0 V N2 (E+Loc N1 destination)] ou 37M5[-N0 V N2 (E+Loc N1 destination)] ou 37M6[-N0 V N2 (E+Loc N1 destination)]" lvf="N3a.1">
     <MEMBERS>
          <MEMBER name="adorner"/>
          <MEMBER name="agrémenter"/>
          <MEMBER name="baliser"/>
          <MEMBER name="chamarrer"/>
          <MEMBER name="dater"/>
          <MEMBER name="décorer"/>
          <MEMBER name="dorer"/>
          <MEMBER name="éclairer"/>
          <MEMBER name="émarger"/>
          <MEMBER name="endosser"/>
          <MEMBER name="enluminer"/>
          <MEMBER name="étiqueter"/>
          <MEMBER name="ferrer"/>
          <MEMBER name="garnir"/>
          <MEMBER name="habiller"/>
          <MEMBER name="illuminer"/>
          <MEMBER name="illustrer"/>
          <MEMBER name="médailler"/>
          <MEMBER name="ornementer"/>
          <MEMBER name="orner"/>
          <MEMBER name="parafer"/>
          <MEMBER name="parer"/>
          <MEMBER name="rehausser"/>
          <MEMBER name="revêtir"/>
          <MEMBER name="tapisser"/>
     </MEMBERS>
     <THEMROLES>
          <THEMROLE type="Agent">
               <SELRESTRS logic="or">
                    <SELRESTR Value="+" type="machine"/>
                    <SELRESTR Value="+" type="animate"/>
               </SELRESTRS>
          </THEMROLE>
          <THEMROLE type="Theme"/>
          <THEMROLE type="Destination">
               <SELRESTR Value="+" type="concrete"/>
          </THEMROLE>
     </THEMROLES>
     <FRAMES>
          <FRAME>
               <DESCRIPTION primary="NP V NP PP.theme"/>
               <EXAMPLES>
                    <EXAMPLE>Luc décorait la bague de/avec son nom.</EXAMPLE>
               </EXAMPLES>
               <SYNTAX>
                    <NP value="Agent">
                         <SYNRESTRS/>
                    </NP>
                    <VERB/>
                    <NP value="Destination">
                         <SYNRESTRS/>
                    </NP>
                    <PREP>
                         <SELRESTRS>
                              <SELRESTR Value="avec;de"/>
                         </SELRESTRS>
                    </PREP>
                    <NP value="Theme">
                         <SYNRESTRS/>
                    </NP>
               </SYNTAX>
               <SEMANTICS>created_image(result(E), Theme) location(end(E), Theme, Destination) cause(Agent, E)</SEMANTICS>
          </FRAME>
     </FRAMES>
</VNCLASS>
